imagejenerator/__init__.py
imagejenerator/config.py
imagejenerator/core/__init__.py
imagejenerator/core/image_generator.py
imagejenerator/examples/config.py
imagejenerator/examples/quick_start.py
imagejenerator/examples/split_workflow.py
imagejenerator/models/__init__.py
imagejenerator/models/registry.py
imagejenerator/models/sd_1_5.py
imagejenerator/models/sd_schedulers.py
imagejenerator/tools/__init__.py
imagejenerator-2.1.0.dist-info/METADATA
imagejenerator-2.1.0.dist-info/WHEEL
imagejenerator-2.1.0.dist-info/licenses/LICENSE
imagejenerator-2.1.0.dist-info/RECORD
