Metadata-Version: 2.4
Name: imagejenerator
Version: 2.1.0
Summary: Image generation suite.
License: MIT
License-File: LICENSE
Author: Warren Davies
Requires-Python: >=3.10,<3.15
Classifier: License :: OSI Approved :: MIT License
Classifier: Operating System :: OS Independent
Classifier: Programming Language :: Python :: 3
Classifier: Programming Language :: Python :: 3.10
Classifier: Programming Language :: Python :: 3.11
Classifier: Programming Language :: Python :: 3.12
Classifier: Programming Language :: Python :: 3.13
Classifier: Programming Language :: Python :: 3.14
Classifier: Topic :: Multimedia :: Graphics :: Graphics Conversion
Classifier: Topic :: Scientific/Engineering :: Artificial Intelligence
Requires-Dist: Pillow (>=10.0)
Requires-Dist: accelerate (>=0.30)
Requires-Dist: diffusers (>=0.35)
Requires-Dist: pyyaml (>=6.0)
Requires-Dist: torch (>=2.9)
Requires-Dist: transformers (>=4.40)
Project-URL: Homepage, https://github.com/WarrenDavies/imagejenerator
Project-URL: Repository, https://github.com/WarrenDavies/imagejenerator
